{"hash":"60068e7bd2bd4dbebea49456db88d79ce1f1da29","data":{"game":{"title":"五色 百人一首 黄","description":"五色百人一首は百人一首を20枚ずつ5色に色分けした教材です。\n札が20枚のため、一試合約3分間で試合をすることができるので、すき間時間でも有効に活用することができます。また、札が20枚ごとに分かれていますので、無理なく覚えられます。\n試合を通して、子供たちには自然と「ルール」が身につき、楽しく仲良く遊べます。\n","credits":[{"license":"","author":"五色百人一首大会 - 公式認定札","link":"https://goshoku.org/official/"},{"license":"CC-BY-SA-3.0","author":"Wikisource - 小倉百人一首","link":"https://ja.wikisource.org/wiki/%E5%B0%8F%E5%80%89%E7%99%BE%E4%BA%BA%E4%B8%80%E9%A6%96"}],"configuration":{"lang":"ja-JP","count":17,"interval":null,"rate":null},"introduction":{"text":"東海の　小島の磯の　白砂に　我泣き濡れて　蟹と戯る","read":"とうかいの、こじまのいその、しらすなに、なきぬれて、かにとたわむる"},"cards":[{"text":"春過ぎて　夏来にけらし　白妙の　衣ほすてふ　天の香具山","read":"はるすぎて、なつきにけらし、しろたへの、ころもほすてふ、あまのかぐやま"},{"text":"天の原　ふりさけ見れば　春日なる　みかさの山に　出でし月かも","read":"あまのはら、ふりさけみれば、かすがなる、みかさのやまに、いでしつきかも"},{"text":"これや此の　行くも帰るも　別かれては　知るも知らぬも　逢坂の関","read":"これやこの、ゆくもかへるも、わかれては、しるもしらぬも、あふさかのせき"},{"text":"住の江の　岸に寄る浪　よるさへや　夢の通ひ路　人目よくらむ","read":"すみのえの、きしによるなみ、よるさへや、ゆめのかよひぢ、ひとめよくらむ"},{"text":"山がはに　風のかけたる　しがらみは　流れもあへぬ　紅葉なりけり","read":"やまがはに、かぜのかけたる、しがらみは、ながれもあへぬ、もみぢなりけり"},{"text":"久方の　光のどけき　春の日に　しづごころなく　花の散るらむ","read":"ひさかたの、ひかりのどけき、はるのひに、しづごころなく、はなのちるらむ"},{"text":"白露に　風の吹きしく　秋の野は　つらぬきとめぬ　玉ぞ散りける","read":"しらつゆに、かぜのふきしく、あきののは、つらぬきとめぬ、たまぞちりける"},{"text":"浅茅生の　小野の篠原　しのぶれど　あまりてなどか　人の戀しき","read":"あさぢふの、をののしのはら、しのぶれど、あまりてなどか、ひとのこひしき"},{"text":"由良の戸を　わたる舟人　楫をたえ　行方もしらぬ　戀の道かな","read":"ゆらのとを、わたるふなびと、かぢをたえ、ゆくへもしらぬ、こひのみちかな"},{"text":"八重葎　しげれる宿の　さびしきに　人こそ見えね　秋はきにけり","read":"やへむぐら、しげれるやどの、さびしきに、ひとこそみえね、あきはきにけり"},{"text":"瀧の音は　たえて久しく　なりぬれど　名こそ流れて　なほ聞えけれ","read":"たきのおとは、たえてひさしく、なりぬれど、なこそながれて、なほきこえけれ"},{"text":"大江山　いくのの道の　遠ければ　まだふみも見ず　天の橋立","read":"おほえやま、いくののみちの、とほければ、まだふみもみず、あまのはしだて"},{"text":"淡路島　かよふ千鳥の　鳴く声に　いくよ寝覚めぬ　須磨の関守","read":"あはぢしま、かよふちどりの、なくこゑに、いくよねざめぬ、すまのせきもり"},{"text":"秋風に　たなびく雲の　絶間より　もれ出づる月の　影のさやけさ","read":"あきかぜに、たなびくくもの、たえまより、もれいづるつきの、かげのさやけさ"},{"text":"ほととぎす　鳴きつる方を　眺むれば　ただ有明の　月ぞ残れる","read":"ほととぎす、なきつるかたを、ながむれば、ただありあけの、つきぞのこれる"},{"text":"村雨の　露もまだひぬ　槙の葉に　霧立ちのぼる　秋の夕暮","read":"むらさめの、つゆもまだひぬ、まきのはに、きりたちのぼる、あきのゆふぐれ"},{"text":"みよし野の　山の秋風　小夜更けて　故郷寒く　衣うつなり","read":"みよしのの、やまのあきかぜ、さよふけて、ふるさとさむく、ころもうつなり"},{"text":"花さそふ　あらしの庭の　雪ならで　ふりゆくものは　我が身なりけり","read":"はなさそふ、あらしのにはの、ゆきならで、ふりゆくものは、わがみなりけり"},{"text":"夜もすがら　もの思ふ頃は　明けやらで　ねやのひまさへ　つれなかりけり","read":"よもすがら、ものおもふころは、あけやらで、ねやのひまさへ、つれなかりけり"},{"text":"玉の緒よ　たえなば絶えね　ながらへば　忍ぶることの　弱りもぞする","read":"たまのをよ、たえなばたえね、ながらへば、しのぶることの、よはりもぞする"}]}},"context":{}}